docs/source/conf.py
mitiq/__init__.py
mitiq/_about.py
mitiq/_version.py
mitiq/typing.py
mitiq/utils.py
mitiq/benchmarks/__init__.py
mitiq/benchmarks/ghz_circuits.py
mitiq/benchmarks/mirror_circuits.py
mitiq/benchmarks/mirror_qv_circuits.py
mitiq/benchmarks/qpe_circuits.py
mitiq/benchmarks/quantum_volume_circuits.py
mitiq/benchmarks/randomized_benchmarking.py
mitiq/benchmarks/randomized_clifford_t_circuit.py
mitiq/benchmarks/rotated_randomized_benchmarking.py
mitiq/benchmarks/w_state_circuits.py
mitiq/benchmarks/tests/test_ghz_circuits.py
mitiq/benchmarks/tests/test_mirror_circuits.py
mitiq/benchmarks/tests/test_mirror_qv_circuits.py
mitiq/benchmarks/tests/test_qpe_circuits.py
mitiq/benchmarks/tests/test_quantum_volume_circuits.py
mitiq/benchmarks/tests/test_randomized_benchmarking.py
mitiq/benchmarks/tests/test_randomized_clifford_t_circuit.py
mitiq/benchmarks/tests/test_rotated_randomized_benchmarking.py
mitiq/benchmarks/tests/test_w_state_circuits.py
mitiq/calibration/__init__.py
mitiq/calibration/calibrator.py
mitiq/calibration/settings.py
mitiq/calibration/tests/test_calibration.py
mitiq/calibration/tests/test_settings.py
mitiq/cdr/__init__.py
mitiq/cdr/_testing.py
mitiq/cdr/cdr.py
mitiq/cdr/clifford_training_data.py
mitiq/cdr/clifford_utils.py
mitiq/cdr/data_regression.py
mitiq/cdr/tests/test_cdr.py
mitiq/cdr/tests/test_clifford_training_data.py
mitiq/cdr/tests/test_clifford_utils.py
mitiq/cdr/tests/test_data_regression.py
mitiq/ddd/__init__.py
mitiq/ddd/ddd.py
mitiq/ddd/insertion.py
mitiq/ddd/rules/__init__.py
mitiq/ddd/rules/rules.py
mitiq/ddd/rules/tests/test_rules.py
mitiq/ddd/tests/test_ddd.py
mitiq/ddd/tests/test_insertion.py
mitiq/executor/__init__.py
mitiq/executor/executor.py
mitiq/executor/tests/test_executor.py
mitiq/interface/__init__.py
mitiq/interface/conversions.py
mitiq/interface/utils.py
mitiq/interface/mitiq_braket/__init__.py
mitiq/interface/mitiq_braket/conversions.py
mitiq/interface/mitiq_braket/tests/test_conversions_braket.py
mitiq-0.48.1.dist-info/licenses/AUTHORS
mitiq-0.48.1.dist-info/licenses/LICENSE
mitiq-0.48.1.dist-info/METADATA
mitiq-0.48.1.dist-info/WHEEL
mitiq-0.48.1.dist-info/top_level.txt
mitiq-0.48.1.dist-info/RECORD
