Metadata-Version: 2.4
Name: mitiq
Version: 0.48.1
Summary: Mitiq is an open source toolkit for implementing error mitigation techniques on most current intermediate-scale quantum computers.
Author-email: Unitary Foundation <info@unitary.foundation>
License: GPL v3.0
Project-URL: Homepage, https://unitary.foundation
Project-URL: Documentation, https://mitiq.readthedocs.io/en/stable/
Project-URL: Repository, https://github.com/unitaryfoundation/mitiq/
Project-URL: Issues, https://github.com/unitaryfoundation/mitiq/issues/
Classifier: Development Status :: 4 - Beta
Classifier: Programming Language :: Python :: 3
Classifier: License :: OSI Approved :: GNU General Public License v3 (GPLv3)
Classifier: Operating System :: MacOS
Classifier: Operating System :: POSIX :: Linux
Classifier: Operating System :: Microsoft :: Windows
Classifier: Topic :: Scientific/Engineering
Classifier: Topic :: Software Development :: Compilers
Classifier: Typing :: Typed
Requires-Python: <3.13,>=3.11
License-File: LICENSE
License-File: AUTHORS
Requires-Dist: numpy<2.0.0,>=1.25.2
Requires-Dist: scipy<=1.16.2,>=1.10.1
Requires-Dist: cirq-core<1.7.0,>=1.6.0
Requires-Dist: tabulate
Requires-Dist: matplotlib>=3.8
Provides-Extra: braket
Requires-Dist: amazon-braket-sdk<1.104,>=1.97; extra == "braket"
Requires-Dist: cirq-ionq<1.7.0,>=1.6.0; extra == "braket"
Provides-Extra: pennylane
Requires-Dist: pennylane-qiskit~=0.43.0; extra == "pennylane"
Requires-Dist: pennylane~=0.43.1; extra == "pennylane"
Provides-Extra: pyquil
Requires-Dist: pyquil~=4.17.0; extra == "pyquil"
Requires-Dist: qbraid~=0.10.0; extra == "pyquil"
Provides-Extra: qibo
Requires-Dist: qibo~=0.2.16; extra == "qibo"
Provides-Extra: qiskit
Requires-Dist: qiskit~=2.0.0; extra == "qiskit"
Requires-Dist: qiskit-aer~=0.17.0; extra == "qiskit"
Requires-Dist: qiskit-ibm-runtime~=0.41.1; extra == "qiskit"
Requires-Dist: ply==3.11; extra == "qiskit"
Dynamic: license-file
